wwpdb/io/__init__.py
wwpdb/io/cvs/CvsAdmin.py
wwpdb/io/cvs/CvsUtility.py
wwpdb/io/cvs/__init__.py
wwpdb/io/file/DataExchange.py
wwpdb/io/file/DataFile.py
wwpdb/io/file/DataMaintenance.py
wwpdb/io/file/ValidateXml.py
wwpdb/io/file/__init__.py
wwpdb/io/file/mmCIFUtil.py
wwpdb/io/graphics/GraphicsContext3D.py
wwpdb/io/graphics/__init__.py
wwpdb/io/locator/ChemRefPathInfo.py
wwpdb/io/locator/DataReference.py
wwpdb/io/locator/PathInfo.py
wwpdb/io/locator/ReleaseFileNames.py
wwpdb/io/locator/ReleasePathInfo.py
wwpdb/io/locator/__init__.py
wwpdb/io/locator/localFTPPathInfo.py
wwpdb/io/misc/Compression.py
wwpdb/io/misc/DataSync.py
wwpdb/io/misc/FormatOut.py
wwpdb/io/misc/SendEmail.py
wwpdb/io/misc/__init__.py
wwpdb/io/sftp/ArchiveIoBase.py
wwpdb/io/sftp/ArchiveIoSftp.py
wwpdb/io/sftp/__init__.py
wwpdb_io-1.0.dist-info/METADATA
wwpdb_io-1.0.dist-info/WHEEL
wwpdb_io-1.0.dist-info/licenses/LICENSE
wwpdb_io-1.0.dist-info/RECORD
