Metadata-Version: 2.4
Name: wwpdb.io
Version: 1.0
Summary: wwPDB Python Configuration Parsing
Project-URL: Homepage, https://github.com/rcsb/py-wwpdb_io
Author-email: Ezra Peisach <ezra.peisach@rcsb.org>
License-Expression: Apache-2.0
License-File: LICENSE
Classifier: Development Status :: 3 - Alpha
Classifier: Intended Audience :: Developers
Classifier: License :: OSI Approved :: Apache Software License
Classifier: Natural Language :: English
Classifier: Programming Language :: Python
Classifier: Programming Language :: Python :: 3
Classifier: Programming Language :: Python :: 3.6
Classifier: Programming Language :: Python :: 3.7
Requires-Python: >=3.6
Requires-Dist: click
Requires-Dist: mmcif-utils
Requires-Dist: mmcif>=0.3
Requires-Dist: paramiko
Requires-Dist: wwpdb-utils-config~=0.40
